README.rst
setup.py
docs/HISTORY.txt
docs/INSTALL.txt
docs/LICENSE.GPL
docs/LICENSE.txt
docs/TODO.txt
jarn/__init__.py
jarn.xmpp.core.egg-info/PKG-INFO
jarn.xmpp.core.egg-info/SOURCES.txt
jarn.xmpp.core.egg-info/dependency_links.txt
jarn.xmpp.core.egg-info/entry_points.txt
jarn.xmpp.core.egg-info/namespace_packages.txt
jarn.xmpp.core.egg-info/not-zip-safe
jarn.xmpp.core.egg-info/requires.txt
jarn.xmpp.core.egg-info/top_level.txt
jarn/xmpp/__init__.py
jarn/xmpp/core/__init__.py
jarn/xmpp/core/client.py
jarn/xmpp/core/configure.zcml
jarn/xmpp/core/interfaces.py
jarn/xmpp/core/settings.py
jarn/xmpp/core/storage.py
jarn/xmpp/core/synci18n.sh
jarn/xmpp/core/testing.py
jarn/xmpp/core/browser/__init__.py
jarn/xmpp/core/browser/configure.zcml
jarn/xmpp/core/browser/loader.py
jarn/xmpp/core/browser/logger.pt
jarn/xmpp/core/browser/pubsub.py
jarn/xmpp/core/browser/pubsub_feed.pt
jarn/xmpp/core/browser/pubsub_item.pt
jarn/xmpp/core/browser/pubsub_portlet.pt
jarn/xmpp/core/browser/pubsub_portlet.py
jarn/xmpp/core/browser/setup.py
jarn/xmpp/core/browser/transforms.py
jarn/xmpp/core/browser/user_details.pt
jarn/xmpp/core/browser/user_profile.pt
jarn/xmpp/core/browser/user_profile.py
jarn/xmpp/core/browser/userinfo.py
jarn/xmpp/core/browser/viewlet.pt
jarn/xmpp/core/browser/viewlet.py
jarn/xmpp/core/browser/css/styles.css
jarn/xmpp/core/browser/gritter/gritter-close-ie6.gif
jarn/xmpp/core/browser/gritter/gritter-long.png
jarn/xmpp/core/browser/gritter/gritter.png
jarn/xmpp/core/browser/gritter/jquery.gritter.css
jarn/xmpp/core/browser/gritter/jquery.gritter.min.js
jarn/xmpp/core/browser/images/chat_icon.png
jarn/xmpp/core/browser/images/location_icon.png
jarn/xmpp/core/browser/images/reply_icon.png
jarn/xmpp/core/browser/images/search_icon.png
jarn/xmpp/core/browser/images/stream_icon.png
jarn/xmpp/core/browser/js/jarnxmpp.core.handlers.js
jarn/xmpp/core/browser/js/jarnxmpp.core.ui.js
jarn/xmpp/core/browser/js/strophe.js
jarn/xmpp/core/locales/jarn.xmpp.core.js.pot
jarn/xmpp/core/locales/jarn.xmpp.core.pot
jarn/xmpp/core/locales/de/LC_MESSAGES/jarn.xmpp.core.js.mo
jarn/xmpp/core/locales/de/LC_MESSAGES/jarn.xmpp.core.js.po
jarn/xmpp/core/locales/de/LC_MESSAGES/jarn.xmpp.core.mo
jarn/xmpp/core/locales/de/LC_MESSAGES/jarn.xmpp.core.po
