Metadata-Version: 1.0
Name: jarn.xmpp.core
Version: 0.31
Summary: Core package for jarn.xmpp
Home-page: https://github.com/ggozad/jarn.xmpp.core
Author: Yiorgis Gozadinos
Author-email: ggozad@jarn.com
License: GPL
Keywords: plone xmpp twisted microblogging
Platform: UNKNOWN
Classifier: Development Status :: 3 - Alpha
Classifier: Framework :: Plone
Classifier: Intended Audience :: Developers
Classifier: Programming Language :: Python
